CHANGES.txt
README.txt
bootstrap.py
buildout.cfg
setup.py
src/zope/__init__.py
src/zope.fssync.egg-info/PKG-INFO
src/zope.fssync.egg-info/SOURCES.txt
src/zope.fssync.egg-info/dependency_links.txt
src/zope.fssync.egg-info/namespace_packages.txt
src/zope.fssync.egg-info/not-zip-safe
src/zope.fssync.egg-info/requires.txt
src/zope.fssync.egg-info/top_level.txt
src/zope/fssync/README.txt
src/zope/fssync/TODO.txt
src/zope/fssync/__init__.py
src/zope/fssync/caseinsensitivity.txt
src/zope/fssync/copier.py
src/zope/fssync/fsmerger.py
src/zope/fssync/fsutil.py
src/zope/fssync/generic.txt
src/zope/fssync/interfaces.py
src/zope/fssync/merger.py
src/zope/fssync/metadata.py
src/zope/fssync/pickle.py
src/zope/fssync/repository.py
src/zope/fssync/snarf.py
src/zope/fssync/svn.py
src/zope/fssync/svn.txt
src/zope/fssync/synchronizer.py
src/zope/fssync/task.py
src/zope/fssync/tests/__init__.py
src/zope/fssync/tests/mockmetadata.py
src/zope/fssync/tests/tempfiles.py
src/zope/fssync/tests/test_docs.py
src/zope/fssync/tests/test_error.py
src/zope/fssync/tests/test_fsmerger.py
src/zope/fssync/tests/test_fsutil.py
src/zope/fssync/tests/test_merger.py
src/zope/fssync/tests/test_metadata.py
src/zope/fssync/tests/test_snarf.py
src/zope/fssync/tests/test_synchronizer.py
src/zope/fssync/tests/test_task.py